{"name":"江泽民","link":"https://baike.baidu.com/link?url=raaDKL_bCS5sXXXuqO_dXZXZFJ9ltthJMopFnIzplnzq2d06z2LX0nQsZPO6O3hDrMjMTJHN_jLCh6j6qlFHKVnM48ENQUaS9lc0d4Hv9FmjjctRQ-5naFuW-rrIdLnG","comment":null,"style":"default","icon":"none","border":"default","id":0,"layer":0,"children":[{"name":"国机二院","link":null,"comment":null,"style":"default","icon":"","border":"default","id":1,"layer":1,"children":[{"name":"几百个教授一致通过","link":null,"comment":null,"style":"default","icon":"none","border":"default","id":4,"layer":2,"children":[{"name":"论文答辩","link":null,"comment":null,"style":"default","icon":"none","border":"default","id":12,"layer":3,"children":[],"parentId":4,"remark":null}],"parentId":1,"remark":null},{"name":"坠痛苦的就是鸭嘴笔","link":null,"comment":null,"style":"default","icon":"none","border":"default","id":6,"layer":2,"children":[{"name":"工程制图","link":null,"comment":null,"style":"default","icon":"none","border":"default","id":13,"layer":3,"children":[],"parentId":6,"remark":null}],"parentId":1,"remark":null}],"parentId":0,"remark":null},{"name":"怒斥港记","link":null,"comment":null,"style":"default","icon":"","border":"default","id":2,"layer":1,"children":[{"name":"跑的比谁都快","link":null,"comment":null,"style":"default","icon":"none","border":"default","id":7,"layer":2,"children":[{"name":"搞个大新闻","link":null,"comment":null,"style":"default","icon":"none","border":"default","id":14,"layer":3,"children":[],"parentId":7,"remark":null}],"parentId":2,"remark":null},{"name":"你问我支持不支持","link":null,"comment":null,"style":"default","icon":"none","border":"default","id":8,"layer":2,"children":[{"name":"我当然是支持的","link":null,"comment":null,"style":"default","icon":"none","border":"default","id":15,"layer":3,"children":[],"parentId":8,"remark":null}],"parentId":2,"remark":null}],"parentId":0,"remark":null},{"name":"谈笑风生","link":null,"comment":null,"style":"default","icon":"","border":"default","id":3,"layer":1,"children":[{"name":"我不是独裁者","link":null,"comment":null,"style":"default","icon":"none","border":"default","id":10,"layer":2,"children":[{"name":"政客不是个好词","link":null,"comment":null,"style":"default","icon":"none","border":"default","id":16,"layer":3,"children":[],"parentId":10,"remark":null}],"parentId":3,"remark":null},{"name":"有时也会阳光灿烂","link":null,"comment":null,"style":"default","icon":"none","border":"default","id":11,"layer":2,"children":[{"name":"中美关系","link":null,"comment":null,"style":"default","icon":"none","border":"default","id":17,"layer":3,"children":[],"parentId":11,"remark":null}],"parentId":3,"remark":null}],"parentId":0,"remark":null}],"parentId":null,"remark":"这是坠吼的!"}